easy_configer/Configer.py
easy_configer/IO_Converter.py
easy_configer/__init__.py
easy_configer/utils/Container.py
easy_configer/utils/Type_Convertor.py
easy_configer-2.5.6.dist-info/METADATA
easy_configer-2.5.6.dist-info/WHEEL
easy_configer-2.5.6.dist-info/top_level.txt
easy_configer-2.5.6.dist-info/RECORD
