Metadata-Version: 2.1
Name: easy-configer
Version: 2.5.6
Summary: An easy way for configurating python program by the given config file or config str
Home-page: https://github.com/HuangChiEn/easy_config
Author: JosefHuang
Author-email: a3285556aa@gmail.com
License: MIT
Keywords: configuration,commendline argument,argument
Classifier: Programming Language :: Python :: 3.6
Classifier: Programming Language :: Python :: 3.7
Classifier: Programming Language :: Python :: 3.8
Classifier: Programming Language :: Python :: 3.9
Requires-Python: >=3.6
